glvars/__init__.py
glvars/config.py
glvars/main.py
glvars/schemas.py
glvars/synchronizer.py
glvars-0.1.5.dist-info/LICENSE
glvars-0.1.5.dist-info/METADATA
glvars-0.1.5.dist-info/WHEEL
glvars-0.1.5.dist-info/entry_points.txt
glvars-0.1.5.dist-info/RECORD
