Metadata-Version: 2.1
Name: glvars
Version: 0.1.5
Summary: CLI utility for managing variables in Gitlab
License: MIT
Author: Alexey Tylindus
Author-email: a.tylindus@gmail.com
Requires-Python: >=3.9,<4.0
Classifier: License :: OSI Approved :: MIT License
Classifier: Programming Language :: Python :: 3
Classifier: Programming Language :: Python :: 3.9
Classifier: Programming Language :: Python :: 3.10
Classifier: Programming Language :: Python :: 3.11
Classifier: Programming Language :: Python :: 3.12
Requires-Dist: PyYAML (>=6.0,<7.0)
Requires-Dist: pydantic (>=2,<3)
Requires-Dist: python-gitlab (>=4.5.0,<5.0.0)
Requires-Dist: typer[all] (>=0.6.1)
